{
    "TConstruct_copper": {
        "template": "uniform",
        "block": "ThermalFoundation:Ore",
        "clusterSize": 8,
        "numClusters": 2,
        "minHeight": 17,
        "maxHeight": 59,
        "retrogen": "true",
        "biomeRestriction": "none",
        "biomes": [
            "all"
        ],
        "dimensionRestriction": "blacklist",
        "dimensions": [
            -1,
            1
        ]
	},
	
	"TConstruct_tin": {
        "template": "uniform",
        "block": {"name": "ThermalFoundation:Ore", "metadata": 1},
        "clusterSize": 7,
        "numClusters": 2,
        "minHeight": 1,
        "maxHeight": 39,
        "retrogen": "true",
        "biomeRestriction": "none",
        "biomes": [
            "all"
        ],
        "dimensionRestriction": "blacklist",
        "dimensions": [
            -1,
            1
        ]
    },
	
	"TConstruct_aluminum": {
        "template": "uniform",
        "block": "ThermalFoundation:Ore",
        "clusterSize": 3,
        "numClusters": 5,
        "minHeight": 1,
        "maxHeight": 62,
        "retrogen": "true",
        "biomeRestriction": "none",
        "biomes": [
            "all"
        ],
        "dimensionRestriction": "blacklist",
        "dimensions": [
            -1,
            1
        ]
    }
}